Dosie/Dosie.pyw
Dosie/__init__.py
Dosie/__main__.py
Dosie/algo.py
Dosie/error.log
Dosie/icon.ico
Dosie/logo.png
Dosie/notifications.py
Dosie/shortcut.vbs
Dosie/startUp.py
Dosie/stats.py
Dosie/access/domains.txt
Dosie/access/downloadableFiles.txt
Dosie/access/history.txt
Dosie/access/keywords.txt
Dosie/access/newDomains.txt
Dosie/access/notifications.txt
Dosie/config/SS_CL_DomainLim.txt
Dosie/config/SS_CL_Relevance.txt
Dosie/config/SS_DL_DomainLim.txt
Dosie/config/SS_DL_ITL.txt
Dosie/config/SS_DL_Relevance.txt
Dosie/config/SS_Relevance.txt
Dosie/folders/folderImages/wv.png
Dosie/img/bb.png
Dosie/img/bh.png
Dosie/img/blueButton.png
Dosie/img/cop.png
Dosie/img/domains.png
Dosie/img/folder.jpg
Dosie/img/folders.png
Dosie/img/google.png
Dosie/img/history.png
Dosie/img/icons8-forward-48.png
Dosie/img/jpg.png
Dosie/img/keywords.png
Dosie/img/kwsv.png
Dosie/img/linkdel.png
Dosie/img/linkdyn.png
Dosie/img/linked.png
Dosie/img/linksave.png
Dosie/img/linksearch.png
Dosie/img/linkstat.png
Dosie/img/load.png
Dosie/img/logo.png
Dosie/img/logo2.png
Dosie/img/lt.png
Dosie/img/media.png
Dosie/img/mp3.png
Dosie/img/mp4.png
Dosie/img/pdf.png
Dosie/img/pers.png
Dosie/img/pin.png
Dosie/img/png.png
Dosie/img/rv.png
Dosie/img/set.png
Dosie/img/set1.png
Dosie/img/set2.png
Dosie/img/set3.png
Dosie/img/txt.png
Dosie/img/wav.png
Dosie/img/wv.png
Dosie/img/xbg.png
Dosie/img/discovered/wv.png
Dosie/img/domainICO/Icon.png
Dosie/img/rel/0.png
Dosie/img/rel/1.png
Dosie/img/rel/10.png
Dosie/img/rel/100.png
Dosie/img/rel/101.png
Dosie/img/rel/102.png
Dosie/img/rel/103.png
Dosie/img/rel/104.png
Dosie/img/rel/105.png
Dosie/img/rel/106.png
Dosie/img/rel/107.png
Dosie/img/rel/108.png
Dosie/img/rel/109.png
Dosie/img/rel/11.png
Dosie/img/rel/110.png
Dosie/img/rel/111.png
Dosie/img/rel/112.png
Dosie/img/rel/113.png
Dosie/img/rel/114.png
Dosie/img/rel/115.png
Dosie/img/rel/116.png
Dosie/img/rel/117.png
Dosie/img/rel/118.png
Dosie/img/rel/119.png
Dosie/img/rel/12.png
Dosie/img/rel/120.png
Dosie-0.0.3.dist-info/LICENSE.txt
Dosie-0.0.3.dist-info/METADATA
Dosie-0.0.3.dist-info/WHEEL
Dosie-0.0.3.dist-info/top_level.txt
Dosie-0.0.3.dist-info/RECORD
