Metadata-Version: 2.1
Name: Dosie
Version: 0.0.3
Summary: A search engine that makes knowledge a resource, and creates liberation with information sharing
Home-page: https://eliezerodjao.com/desktop/portfolio.php?sent=dosie
Author: Eliezer Odjao
Author-email: eliezerodjaoofficial@gmail.com
License: Proprietary
Project-URL: Documentation, https://eliezerodjao.com/docs/Dosie_User0v0v3_Documentation.docx
Project-URL: Source, https://eliezerodjao.com/desktop/portfolio.php?sent=dosie
Keywords: search searchEngine information web internet data
Platform: UNKNOWN
Classifier: Environment :: Win32 (MS Windows)
Classifier: Programming Language :: Python
Classifier: Programming Language :: Python :: 3.4
Classifier: License :: Other/Proprietary License
Classifier: Operating System :: Microsoft :: Windows
Classifier: Development Status :: 3 - Alpha
Classifier: Intended Audience :: End Users/Desktop
Classifier: Natural Language :: English
Classifier: Topic :: Communications
Classifier: Topic :: Education
Classifier: Topic :: Internet
Classifier: Topic :: Internet :: WWW/HTTP :: Browsers
Classifier: Topic :: Internet :: WWW/HTTP :: Indexing/Search
Requires-Python: ~=3.3
Requires-Dist: Synx
Requires-Dist: Pillow
Requires-Dist: requests
